how_to_opensource/__init__.py
how_to_opensource/_version.py
how_to_opensource/core.py
hello_chp-0.1.2.dist-info/LICENSE
hello_chp-0.1.2.dist-info/METADATA
hello_chp-0.1.2.dist-info/WHEEL
hello_chp-0.1.2.dist-info/top_level.txt
hello_chp-0.1.2.dist-info/RECORD
