Metadata-Version: 2.1
Name: hello-chp
Version: 0.1.2
Summary: A Quantmetry tutorial on how to publish an opensource python package.
Home-page: http://packages.python.org/how_to_opensource
Author: Grégoire Martinon, Vianney Taquet, Damien Hervault
Author-email: gmartignon@quantmetry.com
License: BSD
Keywords: example opensource tutorial
Classifier: License :: OSI Approved :: BSD License
Classifier: Programming Language :: Python :: 3.11
License-File: LICENSE
Requires-Dist: numpy (>=1.20)
Provides-Extra: docs
Requires-Dist: sphinx ; extra == 'docs'
Requires-Dist: sphinx-gallery ; extra == 'docs'
Requires-Dist: sphinx-rtd-theme ; extra == 'docs'
Requires-Dist: numpydoc ; extra == 'docs'
Provides-Extra: tests
Requires-Dist: flake8 ; extra == 'tests'
Requires-Dist: mypy ; extra == 'tests'
Requires-Dist: pytest-cov ; extra == 'tests'
